jupyterlab_spreadsheet_editor/__init__.py
jupyterlab_spreadsheet_editor/_version.py
jupyterlab_spreadsheet_editor-0.7.2.data/data/share/jupyter/labextensions/spreadsheet-editor/package.json
jupyterlab_spreadsheet_editor-0.7.2.data/data/share/jupyter/labextensions/spreadsheet-editor/schemas/spreadsheet-editor/package.json.orig
jupyterlab_spreadsheet_editor-0.7.2.data/data/share/jupyter/labextensions/spreadsheet-editor/schemas/spreadsheet-editor/plugin.json
jupyterlab_spreadsheet_editor-0.7.2.data/data/share/jupyter/labextensions/spreadsheet-editor/static/215.2837f1718aac9074a6ab.js
jupyterlab_spreadsheet_editor-0.7.2.data/data/share/jupyter/labextensions/spreadsheet-editor/static/254.8cae1765026eb331001d.js
jupyterlab_spreadsheet_editor-0.7.2.data/data/share/jupyter/labextensions/spreadsheet-editor/static/460.ab00393e0dfc5c2d73ef.js
jupyterlab_spreadsheet_editor-0.7.2.data/data/share/jupyter/labextensions/spreadsheet-editor/static/460.ab00393e0dfc5c2d73ef.js.LICENSE.txt
jupyterlab_spreadsheet_editor-0.7.2.data/data/share/jupyter/labextensions/spreadsheet-editor/static/513.16be2308ac74045cae1f.js
jupyterlab_spreadsheet_editor-0.7.2.data/data/share/jupyter/labextensions/spreadsheet-editor/static/530.57aa316a035c27ee890c.js
jupyterlab_spreadsheet_editor-0.7.2.data/data/share/jupyter/labextensions/spreadsheet-editor/static/remoteEntry.68d9bc68e74e2042d034.js
jupyterlab_spreadsheet_editor-0.7.2.data/data/share/jupyter/labextensions/spreadsheet-editor/static/style.js
jupyterlab_spreadsheet_editor-0.7.2.data/data/share/jupyter/labextensions/spreadsheet-editor/static/third-party-licenses.json
jupyterlab_spreadsheet_editor-0.7.2.data/data/share/jupyter/labextensions/spreadsheet-editor/install.json
jupyterlab_spreadsheet_editor-0.7.2.dist-info/METADATA
jupyterlab_spreadsheet_editor-0.7.2.dist-info/WHEEL
jupyterlab_spreadsheet_editor-0.7.2.dist-info/licenses/LICENSE
jupyterlab_spreadsheet_editor-0.7.2.dist-info/RECORD
