Metadata-Version: 2.3
Name: jupyterlab-spreadsheet-editor
Version: 0.7.2
Dynamic: Keywords
Summary: JupyterLab spreadsheet (csv/tsv) editor
Project-URL: Homepage, https://github.com/jupyterlab-contrib/jupyterlab-spreadsheet-editor
Project-URL: Bug Tracker, https://github.com/jupyterlab-contrib/jupyterlab-spreadsheet-editor/issues
Project-URL: Repository, https://github.com/jupyterlab-contrib/jupyterlab-spreadsheet-editor.git
Author: Michał Krassowski
License: BSD 3-Clause License
License-File: LICENSE
Classifier: Framework :: Jupyter
Classifier: Framework :: Jupyter :: JupyterLab
Classifier: Framework :: Jupyter :: JupyterLab :: 4
Classifier: Framework :: Jupyter :: JupyterLab :: Extensions
Classifier: Framework :: Jupyter :: JupyterLab :: Extensions :: Prebuilt
Classifier: License :: OSI Approved :: BSD License
Classifier: Programming Language :: Python
Classifier: Programming Language :: Python :: 3
Classifier: Programming Language :: Python :: 3.8
Classifier: Programming Language :: Python :: 3.9
Classifier: Programming Language :: Python :: 3.10
Classifier: Programming Language :: Python :: 3.11
Classifier: Programming Language :: Python :: 3.12
Requires-Python: >=3.8
